shopify_client/__init__.py
shopify_client/base_client.py
shopify_client/constants.py
shopify_client/shopify_client_factory.py
shopify_client/versions.py
shopify_client/app/__init__.py
shopify_client/app/client.py
shopify_client/app/app_installation/__init__.py
shopify_client/app/app_installation/client.py
shopify_client/app/app_installation/get.py
shopify_client/app/metafields/__init__.py
shopify_client/app/metafields/client.py
shopify_client/app/metafields/set.py
shopify_client/billing/__init__.py
shopify_client/billing/client.py
shopify_client/billing/constants.py
shopify_client/billing/charges/__init__.py
shopify_client/billing/charges/app_subscription.py
shopify_client/billing/charges/base_charge.py
shopify_client/billing/charges/one_time_purchase.py
shopify_client/billing/schema/__init__.py
shopify_client/billing/schema/objects/__init__.py
shopify_client/billing/schema/objects/subscription.py
shopify_client/billing/schema/requests/__init__.py
shopify_client/billing/schema/requests/app_subscription_request.py
shopify_client/billing/schema/requests/base_charge_request.py
shopify_client/billing/schema/requests/discount.py
shopify_client/billing/schema/requests/discount_value.py
shopify_client/billing/schema/requests/line_item.py
shopify_client/billing/schema/requests/one_time_purchase_request.py
shopify_client/billing/schema/requests/plan.py
shopify_client/billing/schema/requests/price.py
shopify_client/billing/schema/requests/recurring_pricing_details.py
shopify_client/billing/schema/response/__init__.py
shopify_client/billing/schema/response/charge_create_response.py
shopify_client/bulk_operations/__init__.py
shopify_client/bulk_operations/client.py
shopify_client/bulk_operations/get.py
shopify_client/bulk_operations/orders/__init__.py
shopify_client/bulk_operations/orders/client.py
shopify_client/bulk_operations/orders/get.py
shopify_client/common/__init__.py
shopify_client/common/graphql_client.py
shopify_client/common/mixins/__init__.py
shopify_client-4.0.1.dist-info/LICENSE
shopify_client-4.0.1.dist-info/WHEEL
shopify_client-4.0.1.dist-info/METADATA
shopify_client-4.0.1.dist-info/RECORD
