Metadata-Version: 2.1
Name: shopify_client
Version: 4.0.1
Summary: Shopify Client that handles all the network interactions with Shopify
Home-page: https://github.com/Smooth-Code-IO/shopify-client
Author: SmoothCode
Author-email: hello@smoothcode.io
Classifier: License :: OSI Approved :: MIT License
